arrg/__init__.py
arrg/argument.py
arrg/constants.py
arrg/parser.py
arrg/type_resolver.py
arrg/utils.py
arrg-0.1.1.dist-info/METADATA
arrg-0.1.1.dist-info/WHEEL
arrg-0.1.1.dist-info/licenses/LICENSE
arrg-0.1.1.dist-info/RECORD
