Metadata-Version: 2.4
Name: arrg
Version: 0.1.1
Summary: A library for building modular command-line applications
Project-URL: Homepage, https://github.com/terror/arrg
Project-URL: Issues, https://github.com/terror/arrg/issues
License-File: LICENSE
Requires-Python: >=3.12
